vecfield/__init__.py
vecfield/vecfield.py
vecfield-1.0.3.dist-info/LICENSE.txt
vecfield-1.0.3.dist-info/METADATA
vecfield-1.0.3.dist-info/WHEEL
vecfield-1.0.3.dist-info/top_level.txt
vecfield-1.0.3.dist-info/RECORD
