Metadata-Version: 2.1
Name: vecfield
Version: 1.0.3
Summary: Module for working with vector and scalar fields
Home-page: https://github.com/SorbetKipit/jubilant-barnacle/tree/main
Author: SorbetKipit
Author-email: ibk07@yandex.ru
Project-URL: Documentation, https://github.com/SorbetKipit/jubilant-barnacle/blob/main/README.md
Keywords: python vectorifeld scalarfield
Classifier: Programming Language :: Python :: 3.11
Classifier: License :: OSI Approved :: MIT License
Classifier: Operating System :: OS Independent
Requires-Python: >=3.11
License-File: LICENSE.txt
Requires-Dist: sympy >=1.12
Requires-Dist: matplotlib >=3.8.4
Requires-Dist: numpy >=1.26.4
